__init__.py
cli.py
dti.py
main.py
setup.py
visual.py
dti_pipeline-1.0.1.dist-info/METADATA
dti_pipeline-1.0.1.dist-info/WHEEL
dti_pipeline-1.0.1.dist-info/entry_points.txt
dti_pipeline-1.0.1.dist-info/top_level.txt
dti_pipeline-1.0.1.dist-info/RECORD
